esdrt.theme-1.35-py2.7-nspkg.pth
esdrt/theme/__init__.py
esdrt/theme/configure.zcml
esdrt/theme/profiles.zcml
esdrt/theme/rebuild_i18n.sh
esdrt/theme/setuphandlers.py
esdrt/theme/skins.zcml
esdrt/theme/tests.py
esdrt/theme/browser/__init__.py
esdrt/theme/browser/configure.zcml
esdrt/theme/browser/interfaces.py
esdrt/theme/browser/viewlets.py
esdrt/theme/browser/template-overrides/CONTENTS.txt
esdrt/theme/browser/template-overrides/Products.CMFPlone.skins.plone_login.insufficient_privileges.pt
esdrt/theme/browser/template-overrides/Products.CMFPlone.skins.plone_login.insufficient_privileges.pt.metadata
esdrt/theme/browser/template-overrides/Products.CMFPlone.skins.plone_login.login_form.cpt
esdrt/theme/browser/template-overrides/Products.CMFPlone.skins.plone_login.login_form.cpt.metadata
esdrt/theme/browser/template-overrides/Products.CMFPlone.skins.plone_login.require_login.py
esdrt/theme/browser/template-overrides/Products.CMFPlone.skins.plone_templates.global_statusmessage.pt
esdrt/theme/browser/template-overrides/plone.app.discussion.browser.comments.pt
esdrt/theme/browser/template-overrides/plone.app.layout.viewlets.document_byline.pt
esdrt/theme/browser/templates/CONTENTS.txt
esdrt/theme/browser/templates/footer.pt
esdrt/theme/browser/templates/logo.pt
esdrt/theme/browser/templates/personal_bar.pt
esdrt/theme/browser/templates/product_version.pt
esdrt/theme/locales/esdrt.theme-manual.pot
esdrt/theme/locales/esdrt.theme.pot
esdrt/theme/locales/plone.pot
esdrt/theme/locales/en/LC_MESSAGES/esdrt.theme.po
esdrt/theme/locales/en/LC_MESSAGES/plone.po
esdrt/theme/profiles/default/actions.xml
esdrt/theme/profiles/default/cssregistry.xml
esdrt/theme/profiles/default/esdrt.theme_various.txt
esdrt/theme/profiles/default/jsregistry.xml
esdrt/theme/profiles/default/metadata.xml
esdrt/theme/profiles/default/skins.xml
esdrt/theme/profiles/default/viewlets.xml
esdrt/theme/skins/esdrt_theme_images/CONTENT.txt
esdrt/theme/skins/esdrt_theme_images/eea.gif
esdrt.theme-1.35.dist-info/METADATA
esdrt.theme-1.35.dist-info/WHEEL
esdrt.theme-1.35.dist-info/entry_points.txt
esdrt.theme-1.35.dist-info/namespace_packages.txt
esdrt.theme-1.35.dist-info/top_level.txt
esdrt.theme-1.35.dist-info/RECORD
