Metadata-Version: 2.1
Name: esdrt.theme
Version: 1.35
Summary: Installable theme: esdrt.theme
Home-page: https://github.com/eea/esdrt.theme/
Author: Mikel Santamaria
Author-email: msantamaria@bilbomatica.es
License: GPL
Platform: UNKNOWN
Classifier: Framework :: Plone
Classifier: Programming Language :: Python
Requires-Dist: setuptools
Requires-Dist: z3c.jbot
Requires-Dist: five.grok
Requires-Dist: eea.icons
Requires-Dist: esdrt.content
Requires-Dist: Products.Collage
Requires-Dist: eea.controlpanel
